{"metadata": {"dbt_schema_version": "https://schemas.getdbt.com/dbt/run-results/v4.json", "dbt_version": "1.4.0", "generated_at": "2025-12-04T19:25:35.277914Z", "invocation_id": "17c6690e-782c-446e-9e85-c3a3be930c92", "env": {}}, "results": [{"status": "pass", "timing": [{"name": "compile", "started_at": "2025-12-04T19:25:05.279449Z", "completed_at": "2025-12-04T19:25:05.314940Z"}, {"name": "execute", "started_at": "2025-12-04T19:25:05.321913Z", "completed_at": "2025-12-04T19:25:06.976850Z"}], "thread_id": "Thread-2 (worker)", "execution_time": 2.259038209915161, "adapter_response": {}, "message": null, "failures": 0, "unique_id": "test.airflow_dbt_project.is_positive_fact_flights_LATE_AIRCRAFT_DELAY.27b5bdafaa"}, {"status": "pass", "timing": [{"name": "compile", "started_at": "2025-12-04T19:25:05.268824Z", "completed_at": "2025-12-04T19:25:05.297162Z"}, {"name": "execute", "started_at": "2025-12-04T19:25:05.298158Z", "completed_at": "2025-12-04T19:25:06.982385Z"}], "thread_id": "Thread-1 (worker)", "execution_time": 2.2952470779418945, "adapter_response": {}, "message": null, "failures": 0, "unique_id": "test.airflow_dbt_project.is_positive_fact_flights_CARRIER_DELAY.484000faec"}, {"status": "pass", "timing": [{"name": "compile", "started_at": "2025-12-04T19:25:07.567619Z", "completed_at": "2025-12-04T19:25:07.576974Z"}, {"name": "execute", "started_at": "2025-12-04T19:25:07.577964Z", "completed_at": "2025-12-04T19:25:08.991782Z"}], "thread_id": "Thread-1 (worker)", "execution_time": 1.9406888484954834, "adapter_response": {}, "message": null, "failures": 0, "unique_id": "test.airflow_dbt_project.is_positive_fact_flights_SECURITY_DELAY.4501cb0384"}, {"status": "pass", "timing": [{"name": "compile", "started_at": "2025-12-04T19:25:07.533590Z", "completed_at": "2025-12-04T19:25:07.544366Z"}, {"name": "execute", "started_at": "2025-12-04T19:25:07.545340Z", "completed_at": "2025-12-04T19:25:09.054567Z"}], "thread_id": "Thread-2 (worker)", "execution_time": 2.096266508102417, "adapter_response": {}, "message": null, "failures": 0, "unique_id": "test.airflow_dbt_project.is_positive_fact_flights_NAS_DELAY.86e8dba5f3"}, {"status": "pass", "timing": [{"name": "compile", "started_at": "2025-12-04T19:25:09.632037Z", "completed_at": "2025-12-04T19:25:09.638636Z"}, {"name": "execute", "started_at": "2025-12-04T19:25:09.639298Z", "completed_at": "2025-12-04T19:25:10.768589Z"}], "thread_id": "Thread-2 (worker)", "execution_time": 1.8048174381256104, "adapter_response": {}, "message": null, "failures": 0, "unique_id": "test.airflow_dbt_project.is_positive_fact_flights_TAXI_OUT_TIME.0fd7b2b7da"}, {"status": "pass", "timing": [{"name": "compile", "started_at": "2025-12-04T19:25:11.440416Z", "completed_at": "2025-12-04T19:25:11.448302Z"}, {"name": "execute", "started_at": "2025-12-04T19:25:11.449185Z", "completed_at": "2025-12-04T19:25:12.649534Z"}], "thread_id": "Thread-2 (worker)", "execution_time": 1.6172072887420654, "adapter_response": {}, "message": null, "failures": 0, "unique_id": "test.airflow_dbt_project.is_positive_fact_flights_WEATHER_DELAY.e6e4a9b474"}, {"status": "pass", "timing": [{"name": "compile", "started_at": "2025-12-04T19:25:13.065298Z", "completed_at": "2025-12-04T19:25:13.094306Z"}, {"name": "execute", "started_at": "2025-12-04T19:25:13.095350Z", "completed_at": "2025-12-04T19:25:14.132193Z"}], "thread_id": "Thread-2 (worker)", "execution_time": 1.5199823379516602, "adapter_response": {}, "message": null, "failures": 0, "unique_id": "test.airflow_dbt_project.relationships_fact_flights_Actual_Arrival_Time_id__time_id__ref_dim_time_.6d96f941a9"}, {"status": "pass", "timing": [{"name": "compile", "started_at": "2025-12-04T19:25:14.596243Z", "completed_at": "2025-12-04T19:25:14.624390Z"}, {"name": "execute", "started_at": "2025-12-04T19:25:14.626492Z", "completed_at": "2025-12-04T19:25:16.067535Z"}], "thread_id": "Thread-2 (worker)", "execution_time": 1.99884033203125, "adapter_response": {}, "message": null, "failures": 0, "unique_id": "test.airflow_dbt_project.relationships_fact_flights_Actual_Departure_Time_id__time_id__ref_dim_time_.63ef8bb079"}, {"status": "pass", "timing": [{"name": "compile", "started_at": "2025-12-04T19:25:16.592678Z", "completed_at": "2025-12-04T19:25:16.602763Z"}, {"name": "execute", "started_at": "2025-12-04T19:25:16.603446Z", "completed_at": "2025-12-04T19:25:17.777409Z"}], "thread_id": "Thread-2 (worker)", "execution_time": 1.648740291595459, "adapter_response": {}, "message": null, "failures": 0, "unique_id": "test.airflow_dbt_project.relationships_fact_flights_Scheduled_Arrival_Time_id__time_id__ref_dim_time_.69d9d3b608"}, {"status": "pass", "timing": [{"name": "compile", "started_at": "2025-12-04T19:25:18.244039Z", "completed_at": "2025-12-04T19:25:18.253352Z"}, {"name": "execute", "started_at": "2025-12-04T19:25:18.254004Z", "completed_at": "2025-12-04T19:25:19.518992Z"}], "thread_id": "Thread-2 (worker)", "execution_time": 1.7321248054504395, "adapter_response": {}, "message": null, "failures": 0, "unique_id": "test.airflow_dbt_project.relationships_fact_flights_Scheduled_Departure_Time_id__time_id__ref_dim_time_.d3bd2a4932"}, {"status": "pass", "timing": [{"name": "compile", "started_at": "2025-12-04T19:25:19.978796Z", "completed_at": "2025-12-04T19:25:19.987832Z"}, {"name": "execute", "started_at": "2025-12-04T19:25:19.988437Z", "completed_at": "2025-12-04T19:25:22.756472Z"}], "thread_id": "Thread-2 (worker)", "execution_time": 3.3952319622039795, "adapter_response": {}, "message": null, "failures": 0, "unique_id": "test.airflow_dbt_project.relationships_fact_flights_Wheels_Off_Time_id__time_id__ref_dim_time_.c9bc3d25d5"}, {"status": "pass", "timing": [{"name": "compile", "started_at": "2025-12-04T19:25:23.382263Z", "completed_at": "2025-12-04T19:25:23.407563Z"}, {"name": "execute", "started_at": "2025-12-04T19:25:23.409581Z", "completed_at": "2025-12-04T19:25:26.817605Z"}], "thread_id": "Thread-2 (worker)", "execution_time": 4.140925407409668, "adapter_response": {}, "message": null, "failures": 0, "unique_id": "test.airflow_dbt_project.relationships_fact_flights_Wheels_On_Time_id__time_id__ref_dim_time_.6d9f544850"}, {"status": "pass", "timing": [{"name": "compile", "started_at": "2025-12-04T19:25:27.522980Z", "completed_at": "2025-12-04T19:25:27.532687Z"}, {"name": "execute", "started_at": "2025-12-04T19:25:27.533467Z", "completed_at": "2025-12-04T19:25:28.961141Z"}], "thread_id": "Thread-2 (worker)", "execution_time": 2.0367438793182373, "adapter_response": {}, "message": null, "failures": 0, "unique_id": "test.airflow_dbt_project.relationships_fact_flights_date_id__date_id__ref_dim_date_.2df53f44e9"}, {"status": "pass", "timing": [{"name": "compile", "started_at": "2025-12-04T19:25:29.562684Z", "completed_at": "2025-12-04T19:25:29.572988Z"}, {"name": "execute", "started_at": "2025-12-04T19:25:29.573735Z", "completed_at": "2025-12-04T19:25:31.620444Z"}], "thread_id": "Thread-2 (worker)", "execution_time": 2.5367956161499023, "adapter_response": {}, "message": null, "failures": 0, "unique_id": "test.airflow_dbt_project.relationships_fact_flights_destination_id__destination_id__ref_dim_destination_.9490337ee5"}, {"status": "pass", "timing": [{"name": "compile", "started_at": "2025-12-04T19:25:09.508912Z", "completed_at": "2025-12-04T19:25:09.516018Z"}, {"name": "execute", "started_at": "2025-12-04T19:25:09.516742Z", "completed_at": "2025-12-04T19:25:31.798109Z"}], "thread_id": "Thread-1 (worker)", "execution_time": 22.83134961128235, "adapter_response": {}, "message": null, "failures": 0, "unique_id": "test.airflow_dbt_project.is_positive_fact_flights_TAXI_IN_TIME.293996507c"}, {"status": "pass", "timing": [{"name": "compile", "started_at": "2025-12-04T19:25:32.101251Z", "completed_at": "2025-12-04T19:25:32.110517Z"}, {"name": "execute", "started_at": "2025-12-04T19:25:32.111147Z", "completed_at": "2025-12-04T19:25:33.551844Z"}], "thread_id": "Thread-2 (worker)", "execution_time": 2.846850633621216, "adapter_response": {}, "message": null, "failures": 0, "unique_id": "test.airflow_dbt_project.relationships_fact_flights_origin_id__origin_id__ref_dim_origin_.b37c81fa24"}, {"status": "pass", "timing": [{"name": "compile", "started_at": "2025-12-04T19:25:32.342759Z", "completed_at": "2025-12-04T19:25:32.351691Z"}, {"name": "execute", "started_at": "2025-12-04T19:25:32.352321Z", "completed_at": "2025-12-04T19:25:34.519220Z"}], "thread_id": "Thread-1 (worker)", "execution_time": 2.9107537269592285, "adapter_response": {}, "message": null, "failures": 0, "unique_id": "test.airflow_dbt_project.relationships_fact_flights_status_id__status_id__ref_dim_flight_status_.a647fbaaaa"}], "elapsed_time": 56.21950888633728, "args": {"write_json": true, "use_colors": true, "printer_width": 80, "version_check": true, "partial_parse": true, "static_parser": true, "profiles_dir": "/opt/airflow/dbt", "send_anonymous_usage_stats": true, "quiet": false, "no_print": false, "cache_selected_only": false, "project_dir": "/opt/airflow/dbt", "indirect_selection": "eager", "select": ["test_type:generic"], "which": "test", "rpc_method": "test"}}